pif_importer/__init__.py
pif_importer/pif_importer.py
pif_ingestor/__init__.py
pif_ingestor/pif_ingestor.py
pif_ingestor-0.1.0.dist-info/DESCRIPTION.rst
pif_ingestor-0.1.0.dist-info/METADATA
pif_ingestor-0.1.0.dist-info/RECORD
pif_ingestor-0.1.0.dist-info/WHEEL
pif_ingestor-0.1.0.dist-info/entry_points.txt
pif_ingestor-0.1.0.dist-info/metadata.json
pif_ingestor-0.1.0.dist-info/top_level.txt
