Metadata-Version: 2.0
Name: pif-ingestor
Version: 0.1.0
Summary: Script to ingest common data formats into Citrination
Home-page: http://github.com/CitrineInformatics/pif-ingestor
Author: Max Hutchinson
Author-email: maxhutch@citrine.io
License: UNKNOWN
Platform: UNKNOWN
Requires-Dist: citrination-client
Requires-Dist: pypif
Requires-Dist: stevedore
